Metadata-Version: 2.1
Name: local_vector_search
Version: 0.0.1
Summary: Create document embeddings for RAG
Home-page: https://github.com/dhopp1/local_vector_search
Author: Daniel Hopp
Author-email: daniel.hopp@un.org
Classifier: Programming Language :: Python :: 3
Classifier: License :: OSI Approved :: MIT License
Classifier: Operating System :: OS Independent
Requires-Python: >=3.6
License-File: LICENSE
